dpt_builder_suite/__init__.py
dpt_builder_suite/builder_skel.py
dpt_builder_suite/copy_builder.py
dpt_builder_suite/py_builder.py
dpt_builder_suite/distutils/__init__.py
dpt_builder_suite/distutils/build_mixin.py
dpt_builder_suite/distutils/build_py.py
dpt_builder_suite/distutils/install_copied_and_extended_data.py
dpt_builder_suite/distutils/install_data.py
dpt_builder_suite/distutils/sdist.py
dpt_builder_suite/distutils/temporary_directory.py
dpt_builder_suite-1.0.4.data/data/docs/LICENSE
dpt_builder_suite-1.0.4.data/data/docs/README
dpt_builder_suite-1.0.4.data/scripts/make.py
dpt_builder_suite-1.0.4.data/scripts/make_py.py
dpt_builder_suite-1.0.4.dist-info/LICENSE
dpt_builder_suite-1.0.4.dist-info/METADATA
dpt_builder_suite-1.0.4.dist-info/WHEEL
dpt_builder_suite-1.0.4.dist-info/top_level.txt
dpt_builder_suite-1.0.4.dist-info/RECORD
