Metadata-Version: 2.1
Name: dpt-builder-suite
Version: 1.0.4
Summary: Build code for different release targets
Home-page: https://www.direct-netware.de/redirect?dpt;builder_suite
Author: direct Netware Group et al.
Author-email: web@direct-netware.de
License: MPL2
Platform: any
Classifier: Intended Audience :: Developers
Classifier: License :: OSI Approved :: Mozilla Public License 2.0 (MPL 2.0)
Classifier: Operating System :: OS Independent
Classifier: Programming Language :: Python
Classifier: Topic :: Software Development :: Build Tools
Requires-Dist: dpt-file (<2,>=1)
